Workbook

Sheet Resumo & Apuração
A1: DECLARAÇÃO DO IMPOSTO DE RENDA - PESSOA FÍSICA (IRPF)
A2: Simulador e Calculadora de Apuração IRPF / Tabela Progressiva
A4: 1. DADOS DO CONTRIBUINTE E TIPO DE DECLARAÇÃO
A5: Nome do Contribuinte: | B5: Nome Exemplo | C5: CPF: | D5: 000.000.000-00
A6: Ano-Calendário: | B6: 2025 | C6: Exercício: | D6: 2026
A7: Opção de Tributação Preferencial: | B7: Comparativo (Menor Imposto)
A9: 2. APURAÇÃO COMPARATIVA: SIMPLIFICADO VS. COMPLETO
A10: Descrição | B10: Dedução Simplificada | C10: Dedução Completa | D10: Observações / Origem
A11: Total de Rendimentos Tributáveis | B11: =Rendimentos!D19 | C11: =Rendimentos!D19 | D11: Soma de salários, pró-labore, aluguéis, etc.
A12: (-) Total de Deduções Legais | B12: =MIN('Rendimentos'!D19*0.2, 16754.34) | C12: ='Deduções'!D18 | D12: Simplificado limit. R$ 16.754,34 (20%)
A13: (=) Base de Calculo do Imposto | B13: =MAX(0, B11-B12) | C13: =MAX(0, C11-C12) | D13: Rendimentos TRIBUTÁVEIS (-) Deduções
A14: Imposto Devido (Tabela Progressiva) | B14: =MAX(0, (B13*0.275)-10842.24) | C14: =MAX(0, (C13*0.275)-10842.24) | D14: Cálculo aproximado faixa máx/progressiva
A15: (-) Imposto Pego na Fonte / Recolhido | B15: =Rendimentos!E19 | C15: =Rendimentos!E19 | D15: Retido pela fonte pagadora (IRRF)
A16: (=) IMPOSTO A PAGAR / (RESTITUIÇÃO) | B16: =B14-B15 | C16: =C14-C15 | D16: Valor positivo = Pagar | Negativo = Restituir
A18: 3. RECOMENDAÇÃO E DIAGNÓSTICO DA DECLARAÇÃO
A19: Opção Mais Vantajosa: | B19: =IF(B16<C16, "DESCONTO SIMPLIFICADO", IF(C16<B16, "DEDUÇÕES COMPLETAS", "AMBAS EQUIVALENTES"))
A20: Resultado Estimado: | B20: =IF(MIN(B16,C16)<0, "RESTITUIÇÃO DE " & TEXT(ABS(MIN(B16,C16)), "R$ #,##0.00"), "IMPOSTO A PAGAR DE " & TEXT(MIN(B16,C16), "R$ #,##0.00"))
A22: 4. TABELA PROGRESSIVA MENSAL / ANUAL DE REFERÊNCIA
A23: Base de Cálculo Anual (R$) | B23: Alíquota (%) | C23: Parcela a Duzir do Imposto (R$) | D23: Faixa
A24: Até R$ 28.286,57 | B24: 0 | C24: 0 | D24: Isento
A25: De R$ 28.286,58 até R$ 35.089,20 | B25: 0.075 | C25: 2121.49 | D25: Faixa 2
A26: De R$ 35.089,21 até R$ 46.646,88 | B26: 0.15 | C26: 4753.18 | D26: Faixa 3
A27: De R$ 46.646,89 até R$ 58.211,00 | B27: 0.225 | C27: 8251.7 | D27: Faixa 4
A28: Acima de R$ 58.211,00 | B28: 0.275 | C28: 11162.25 | D28: Faixa 5

Sheet Rendimentos
A1: INFORME DE RENDIMENTOS RECEBIDOS (ANO-CALENDÁRIO)
A2: Informe os rendimentos tributáveis, isentos e tributados na fonte
A4: 1. RENDIMENTOS TRIBUTÁVEIS DE PESSOAS JURÍDICAS OU FÍSICAS
A5: Fonte Pagadora / Fonte | B5: CNPJ / CPF | C5: Rendimento Bruto (R$) | D5: Contribuição Previdenciária (R$) | E5: IRRF Retido na Fonte (R$) | F5: 13º Salário (R$)
A6: Empresa ABC Ltda | B6: 12.345.678/0001-90 | C6: 85000 | D6: 9200 | E6: 11500 | F6: 7000
A7: Aluguéis Recebidos | B7: 111.222.333-44 | C7: 18000 | D7: 0 | E7: 0 | F7: 0
A8: Serviços Prestados (Autônomo) | B8: 55.666.777/0001-11 | C8: 12000 | D8: 1320 | E8: 600 | F8: 0
C9: 0 | D9: 0 | E9: 0 | F9: 0
C10: 0 | D10: 0 | E10: 0 | F10: 0
C11: 0 | D11: 0 | E11: 0 | F11: 0
C12: 0 | D12: 0 | E12: 0 | F12: 0
C13: 0 | D13: 0 | E13: 0 | F13: 0
C14: 0 | D14: 0 | E14: 0 | F14: 0
C15: 0 | D15: 0 | E15: 0 | F15: 0
C16: 0 | D16: 0 | E16: 0 | F16: 0
C17: 0 | D17: 0 | E17: 0 | F17: 0
A19: TOTAL DE RENDIMENTOS TRIBUTÁVEIS | C19: =SUM(C6:C18) | D19: =SUM(D6:D18) | E19: =SUM(E6:E18) | F19: =SUM(F6:F18)
A22: 2. RENDIMENTOS ISENTOS E NÃO TRIBUTÁVEIS
A23: Tipo de Rendimento Isento | B23: CNPJ/CPF Fonte | C23: Descrição / Origem | D23: Valor (R$)
A24: Rendimento de Caderneta de Poupança / LCI / LCA | B24: 00.000.000/0001-00 | C24: Banco Rendimentos | D24: 2400
A25: Lucros e Dividendos Recebidos | B25: 12.345.678/0001-90 | C25: Empresa ABC Ltda | D25: 15000
A26: Indenizações por Rescisão de Contrato de Trabalho | D26: 0
A27: Outros Isentos | D27: 0
A28: TOTAL RENDIMENTOS ISENTOS | D28: =SUM(D24:D27)

Sheet Deduções
A1: DEDUÇÕES LEGAIS (DECLARAÇÃO COMPLETA)
A2: Cadastre dependentes, despesas médicas, instrução, previdência e pensão
A4: 1. DEPENDENTES (Dedução fixa de R$ 2.275,08 por dependente/ano)
A5: Nome do Dependente | B5: CPF | C5: Data Nascimento | D5: Grau de Parentesco | E5: Valor Dedução (R$)
A6: Filho Exemplo 1 | B6: 000.111.222-33 | C6: 15/05/2015 | D6: Filho(a) | E6: 2275.08
A7: Cônjuge Exemplo | B7: 999.888.777-66 | C7: 20/10/1988 | D7: Cônjuge | E7: 2275.08
E8: 0
A9: TOTAL DEDUÇÃO DEPENDENTES | E9: =SUM(E6:E8)
A11: 2. DESPESAS DEDUTÍVEIS (SAÚDE, EDUCAÇÃO, PGBL, PENSÃO ALIMENTÍCIA)
A12: Categoria | B12: Beneficiário / Prestador | C12: CNPJ / CPF Prestador | D12: Valor Pago (R$) | E12: Dedução Efetiva / Limite (R$)
A13: Instrução / Educação | B13: Escola Exemplo | C13: 11.222.333/0001-44 | D13: 5000 | E13: =MIN(D13, 3561.50)
A14: Instrução / Educação | B14: Faculdade Exemplo | C14: 44.555.666/0001-77 | D14: 4000 | E14: =MIN(D14, 3561.50)
A15: Despesa Médica / Saúde | B15: Plano de Saúde Unimed | C15: 88.999.000/0001-11 | D15: 7200 | E15: =D15
A16: Despesa Médica / Saúde | B16: Consultas e Exames | C16: 000.111.222-99 | D16: 1800 | E16: =D16
A17: Previdência Privada (PGBL) | B17: Fundo PGBL Banco | C17: 55.444.333/0001-22 | D17: 6000 | E17: =MIN(D17, Rendimentos!D19*0.12)
A18: TOTAL GERAL DE DEDUÇÕES LEGAIS | D18: =SUM(D13:D17)+Rendimentos!D19 | E18: =E9+SUM(E13:E17)+Rendimentos!D19

Sheet Bens e Direitos
A1: DECLARAÇÃO DE BENS E DIREITOS
A2: Acompanhamento da evolução patrimonial entre 31/12 do ano anterior e 31/12 do ano-calendário
A4: RELAÇÃO DE BENS, DIREITOS, IMÓVEIS, VEÍCULOS E APLICAÇÕES
A5: Grupo / Código | B5: Discriminação e Detalhamento do Bem | C5: Localização / Documento | D5: Situação em 31/12/2024 (R$) | E5: Situação em 31/12/2025 (R$) | F5: Variação Patrimonial (R$)
A6: 01 - Imóveis (01-Apartamento) | B6: Apartamento de 85m², R. Exemplo nº 100, SP | C6: Matrícula 123456 | D6: 350000 | E6: 370000 | F6: =E6-D6
A7: 02 - Veículos (01-Automóvel) | B7: Veículo SUV Modelo 2022, Placa ABC-1234 | C7: Renavam 00000000 | D7: 95000 | E7: 85000 | F7: =E7-D7
A8: 04 - Aplicações (02-Ações) | B8: Lote de Ações PETR4, Custódia Corretora | C8: CNPJ Corretora | D8: 15000 | E8: 22000 | F8: =E8-D8
A9: 07 - Depósitos à Vista (01-Conta) | B9: Saldo em Conta Corrente Banco Itaú | C9: Ag 1234 CC 56789 | D9: 5400 | E9: 12800 | F9: =E9-D9
D10: 0 | E10: 0 | F10: =E10-D10
D11: 0 | E11: 0 | F11: =E11-D11
D12: 0 | E12: 0 | F12: =E12-D12
A13: TOTAL PATRIMÔNIO DECLARADO | D13: =SUM(D6:D12) | E13: =SUM(E6:E12) | F13: =SUM(F6:F12)

Sheet Renda Variável & FIIs
A1: APURAÇÃO DE RENDA VARIÁVEL E AÇÕES (MENSAL)
A2: Controle mensal de lucros/prejuízos em Operações Comuns, Day Trade e FIIs
A4: CONTROLE DE OPERAÇÕES EM BOLSA DE VALORES
A5: Mês | B5: Lucro/Prejuízo Ações Comum (R$) | C5: Lucro/Prejuízo Day Trade (R$) | D5: Lucro/Prejuízo FIIs (R$) | E5: Prejuízo Acumulado Anterior (R$) | F5: Imposto Devido (R$) | G5: IRRF Pago no Mês (R$)
A6: Janeiro | B6: 0 | C6: 0 | D6: 0 | E6: 0 | F6: =MAX(0, (B6*0.15) + (C6*0.20) + (D6*0.20)) | G6: 0
A7: Fevereiro | B7: 0 | C7: 0 | D7: 0 | E7: 0 | F7: =MAX(0, (B7*0.15) + (C7*0.20) + (D7*0.20)) | G7: 0
A8: Março | B8: 0 | C8: 0 | D8: 0 | E8: 0 | F8: =MAX(0, (B8*0.15) + (C8*0.20) + (D8*0.20)) | G8: 0
A9: Abril | B9: 0 | C9: 0 | D9: 0 | E9: 0 | F9: =MAX(0, (B9*0.15) + (C9*0.20) + (D9*0.20)) | G9: 0
A10: Maio | B10: 0 | C10: 0 | D10: 0 | E10: 0 | F10: =MAX(0, (B10*0.15) + (C10*0.20) + (D10*0.20)) | G10: 0
A11: Junho | B11: 0 | C11: 0 | D11: 0 | E11: 0 | F11: =MAX(0, (B11*0.15) + (C11*0.20) + (D11*0.20)) | G11: 0
A12: Julho | B12: 0 | C12: 0 | D12: 0 | E12: 0 | F12: =MAX(0, (B12*0.15) + (C12*0.20) + (D12*0.20)) | G12: 0
A13: Agosto | B13: 0 | C13: 0 | D13: 0 | E13: 0 | F13: =MAX(0, (B13*0.15) + (C13*0.20) + (D13*0.20)) | G13: 0
A14: Setembro | B14: 0 | C14: 0 | D14: 0 | E14: 0 | F14: =MAX(0, (B14*0.15) + (C14*0.20) + (D14*0.20)) | G14: 0
A15: Outubro | B15: 0 | C15: 0 | D15: 0 | E15: 0 | F15: =MAX(0, (B15*0.15) + (C15*0.20) + (D15*0.20)) | G15: 0
A16: Novembro | B16: 0 | C16: 0 | D16: 0 | E16: 0 | F16: =MAX(0, (B16*0.15) + (C16*0.20) + (D16*0.20)) | G16: 0
A17: Dezembro | B17: 0 | C17: 0 | D17: 0 | E17: 0 | F17: =MAX(0, (B17*0.15) + (C17*0.20) + (D17*0.20)) | G17: 0
A18: TOTAL ANUAL | B18: =SUM(B6:B17) | C18: =SUM(C6:C17) | D18: =SUM(D6:D17) | E18: =SUM(E6:E17) | F18: =SUM(F6:F17) | G18: =SUM(G6:G17)
