Workbook
Name salario: 'Simulador FII'!$C$6
Name aporte_sugerido: 'Simulador FII'!$C$7
Name aporte: 'Simulador FII'!$C$8
Name anos: 'Simulador FII'!$C$9
Name taxa_mensal: 'Simulador FII'!$C$10
Name perfil: 'Simulador FII'!$C$11
Name patrimonio_acumulado: 'Simulador FII'!$F$6
Name dividendos_mensais: 'Simulador FII'!$F$7
Name dividendos_anuais: 'Simulador FII'!$F$8
Name total_aportado: 'Simulador FII'!$F$9
Name total_juros: 'Simulador FII'!$F$10

Sheet Simulador FII
B2: SIMULADOR DE INVESTIMENTO EM FUNDOS IMOBILIÁRIOS (FIIs)
B3: Planejamento de Longo Prazo, Patrimônio e Dividendos Mensais
B5: PARÂMETROS DA SIMULAÇÃO | E5: RESULTADOS DA SIMULAÇÃO
B6: Salário Mensal (R$): | C6: 5000 | E6: Patrimônio Acumulado Estimado: | F6: =-VF(taxa_mensal; anos*12; aporte)
B7: Sugestão de Aporte (30%): | C7: =B6*0.30 | E7: Rendimento Mensal em Dividendos: | F7: =patrimonio_acumulado*taxa_mensal
B8: Aporte Mensal Desejado (R$): | C8: 1500 | E8: Rendimento Anual em Dividendos: | F8: =dividendos_mensais*12
B9: Anos de Investimento: | C9: 10 | E9: Total de Aportes Efetuados: | F9: =aporte*anos*12
B10: Taxa de Rendimento Mensal (%): | C10: 0.008 | E10: Total Ganho em Juros/Rendimentos: | F10: =patrimonio_acumulado-total_aportado
B11: Perfil de Investidor: | C11: Moderado
B13: PROJEÇÃO DE CENÁRIOS DE TEMPO
B14: Prazo (Anos) | C14: Total Aportado (R$) | D14: Patrimônio Acumulado (R$) | E14: Dividendo Mensal Estimado (R$)
B15: 2 | C15: =aporte*B15*12 | D15: =-VF(taxa_mensal; B15*12; aporte) | E15: =D15*taxa_mensal
B16: 5 | C16: =aporte*B16*12 | D16: =-VF(taxa_mensal; B16*12; aporte) | E16: =D16*taxa_mensal
B17: 10 | C17: =aporte*B17*12 | D17: =-VF(taxa_mensal; B17*12; aporte) | E17: =D17*taxa_mensal
B18: 20 | C18: =aporte*B18*12 | D18: =-VF(taxa_mensal; B18*12; aporte) | E18: =D18*taxa_mensal
B19: 30 | C19: =aporte*B19*12 | D19: =-VF(taxa_mensal; B19*12; aporte) | E19: =D19*taxa_mensal
B22: DIVISÃO DO APORTE POR TIPO DE FII
B23: Tipo de Fundo Imobiliário | C23: % Alocação | D23: Aporte Mensal (R$) | E23: Dividendo Mensal Estimado (R$)
B24: FIIs de Tijolo (Corporativo / Logística / Shopping) | C24: =PROCV(perfil&"_"&B24; Apoio!$A$2:$D$19; 4; FALSO) | D24: =aporte*C24 | E24: =dividendos_mensais*C24
B25: FIIs de Papel (CRIs / Títulos Dívida Imobiliária) | C25: =PROCV(perfil&"_"&B25; Apoio!$A$2:$D$19; 4; FALSO) | D25: =aporte*C25 | E25: =dividendos_mensais*C25
B26: FIIs de Fundos (FoFs) | C26: =PROCV(perfil&"_"&B26; Apoio!$A$2:$D$19; 4; FALSO) | D26: =aporte*C26 | E26: =dividendos_mensais*C26
B27: FIIs de Desenvolvimento (Obras / Incorporação) | C27: =PROCV(perfil&"_"&B27; Apoio!$A$2:$D$19; 4; FALSO) | D27: =aporte*C27 | E27: =dividendos_mensais*C27
B28: FIIs Híbridos | C28: =PROCV(perfil&"_"&B28; Apoio!$A$2:$D$19; 4; FALSO) | D28: =aporte*C28 | E28: =dividendos_mensais*C28
B29: Fiagros / Outros | C29: =PROCV(perfil&"_"&B29; Apoio!$A$2:$D$19; 4; FALSO) | D29: =aporte*C29 | E29: =dividendos_mensais*C29
B30: TOTAL | C30: =SOMA(C24:C29) | D30: =SOMA(D24:D29) | E30: =SOMA(E24:E29)
B32: * Células cinzas/azuladas são calculadas automaticamente. Altere apenas os parâmetros de entrada em cinza claro.

Sheet Apoio
A1: Chave_Composta | B1: Perfil | C1: Tipo_Fundo | D1: Percentual | F1: Perfis_Disponiveis
A2: =B2&"_"&C2 | B2: Conservador | C2: FIIs de Tijolo (Corporativo / Logística / Shopping) | D2: 0.5 | F2: Conservador
A3: =B3&"_"&C3 | B3: Conservador | C3: FIIs de Papel (CRIs / Títulos Dívida Imobiliária) | D3: 0.3 | F3: Moderado
A4: =B4&"_"&C4 | B4: Conservador | C4: FIIs de Fundos (FoFs) | D4: 0.1 | F4: Arrojado
A5: =B5&"_"&C5 | B5: Conservador | C5: FIIs de Desenvolvimento (Obras / Incorporação) | D5: 0
A6: =B6&"_"&C6 | B6: Conservador | C6: FIIs Híbridos | D6: 0.1
A7: =B7&"_"&C7 | B7: Conservador | C7: Fiagros / Outros | D7: 0
A8: =B8&"_"&C8 | B8: Moderado | C8: FIIs de Tijolo (Corporativo / Logística / Shopping) | D8: 0.4
A9: =B9&"_"&C9 | B9: Moderado | C9: FIIs de Papel (CRIs / Títulos Dívida Imobiliária) | D9: 0.25
A10: =B10&"_"&C10 | B10: Moderado | C10: FIIs de Fundos (FoFs) | D10: 0.15
A11: =B11&"_"&C11 | B11: Moderado | C11: FIIs de Desenvolvimento (Obras / Incorporação) | D11: 0.05
A12: =B12&"_"&C12 | B12: Moderado | C12: FIIs Híbridos | D12: 0.1
A13: =B13&"_"&C13 | B13: Moderado | C13: Fiagros / Outros | D13: 0.05
A14: =B14&"_"&C14 | B14: Arrojado | C14: FIIs de Tijolo (Corporativo / Logística / Shopping) | D14: 0.25
A15: =B15&"_"&C15 | B15: Arrojado | C15: FIIs de Papel (CRIs / Títulos Dívida Imobiliária) | D15: 0.2
A16: =B16&"_"&C16 | B16: Arrojado | C16: FIIs de Fundos (FoFs) | D16: 0.15
... A19: =B19&"_"&C19 | B19: Arrojado | C19: Fiagros / Outros | D19: 0.1
